{
  "openapi": "3.0.1",
  "info": {
    "title": "Cara ou coroa API",
    "description": "Api que retorna um aleatório para cara ou coroa",
    "contact": {
      "name": "Leonardo Souza",
      "url": "https://github.com/ltreze"
    },
    "version": "v1"
  },
  "paths": {
    "/": {
      "get": {
        "tags": [
          "Jogar"
        ],
        "responses": {
          "200": {
            "description": "Success",
            "content": {
              "text/plain": {
                "schema": {
                  "$ref": "#/components/schemas/CaraOuCoroaResultado"
                }
              },
              "application/json": {
                "schema": {
                  "$ref": "#/components/schemas/CaraOuCoroaResultado"
                }
              },
              "text/json": {
                "schema": {
                  "$ref": "#/components/schemas/CaraOuCoroaResultado"
                }
              }
            }
          }
        }
      }
    }
  },
  "components": {
    "schemas": {
      "CaraOuCoroaResultado": {
        "type": "object",
        "properties": {
          "resultado": {
            "type": "string",
            "nullable": true
          }
        },
        "additionalProperties": false
      }
    }
  }
}